{
  "id": "S18E3",
  "name": "第18赛季·精华3",
  "essenceImage": "./img/q5ep7mlrajvlnrrl12333g3oa1c7okp.png",
  "diff_A": 2,
  "initialCurrencies": {
    "inspiration": 100000,
    "fragments": 0
  },
  "discounts": [
    {
      "name": "-20%",
      "rate": 0.8,
      "chance": 0.03
    },
    {
      "name": "-40%",
      "rate": 0.6,
      "chance": 0.015
    }
  ],
  "fragmentsInfo": {
    "name": "碎片",
    "img": "./img/417bhrchsnd048x8yuxf62mrmmp6l1p.png",
    "type": "通用货币"
  },
  "pitySettings": {
    "gold": 250,
    "purple": 60,
    "blue": 10
  },
  "items": {
    "S": [
      {
        "name": "红衣人",
        "img": "./img/k8jiy41rgnwxr113qu91d6btp9a8zgn.png",
        "type": "时装",
        "description": "你的恐惧，“他”的血肉，一场最后的狂欢。\n（【限定】时装，仅能在第十八赛季精华3中获得）",
        "repeat": 2000
      }
    ],
    "A": [
      {
        "name": "逃亡者",
        "img": "./img/at2re6phuv33x2bpolff9r06oin2xsd.png",
        "type": "时装",
        "description": "无法理解恐惧的绝望，才勇于伸手抓住命运之绳。",
        "repeat": 1000
      },
      {
        "name": "窥伺之心",
        "img": "./img/r70bf6rbkuxvi3epb8hmp1wk7gmurgw.png",
        "type": "时装",
        "description": "上天给予的美貌与宠爱并不是肥沃的土壤，不足以拯救日益枯萎的花。",
        "repeat": 1000
      }
    ],
    "B": [
      {
        "name": "“鸵鸟”",
        "img": "./img/8cmax1xrztus1oomn4t342ne8bqabbs.png",
        "type": "时装",
        "description": "无罪者自我麻痹，以期逃脱无妄之渊。",
        "repeat": 200
      },
      {
        "name": "得利者",
        "img": "./img/5n5vt07w02gvum3wgq1a7iky3tm66jx.png",
        "type": "时装",
        "description": "所谓的是与非，对与错，又与她何干?",
        "repeat": 200
      },
      {
        "name": "忠实的仆人",
        "img": "./img/b23fl2ryhoh57803dhpd9mjkof5e03j.png",
        "type": "时装",
        "description": "七，是走廊尽头房间的数字，也是恶魔胜利的那天。",
        "repeat": 200
      },
      {
        "name": "懦弱者",
        "img": "./img/7wqytfhhwrfjk1sol10ycqg91ygzurr.png",
        "type": "时装",
        "description": "被恐惧所支配的人啊，一心渴求维持虚假现状。",
        "repeat": 200
      },
      {
        "name": "“寄居蟹”",
        "img": "./img/tho7oho5cuokhd2uqgk257vrzaexzag.png",
        "type": "时装",
        "description": "当你的肉体被摧毁时，你失去的是一部分的自己，当你的精神也低头时，便失去了全部的自己。",
        "repeat": 200
      },
      {
        "name": "深渊符号",
        "img": "./img/0xb44dxp38s60pcxjzifk8b0317jjul.png",
        "type": "时装",
        "description": "他深知自己的琴弦不能将大家带往艺术的天堂。",
        "repeat": 200
      },
      {
        "name": "画家-起舞",
        "img": "./img/73nip7a7kcx0arn2v8y72o5xt153jyc.png",
        "type": "个性动作",
        "description": "起舞动作，画家专属",
        "repeat": 200
      },
      {
        "name": "“博士”-行礼",
        "img": "./img/jvroaff1gx4rz5tt2ke934hrhhs2z5i.png",
        "type": "个性动作",
        "description": "行礼动作，“博士”专属",
        "repeat": 200
      },
      {
        "name": "守墓人-小憩",
        "img": "./img/0w1n2jkyzmbjhi6oml4j01c4ou56zku.png",
        "type": "等待动作",
        "description": "守墓人专属匹配大厅等待动作，小憩",
        "repeat": 200
      },
      {
        "name": "画家-张望",
        "img": "./img/0w1n2jkyzmbjhi6oml4j01c4ou56zku.png",
        "type": "等待动作",
        "description": "画家匹配大厅动作，张望",
        "repeat": 200
      }
    ],
    "C": [
      {
        "name": "平凡灰",
        "img": "./img/47bgew6utc67g339kgmng0efe496hw6.png",
        "type": "时装",
        "description": "平平淡淡的人生有什么不好！",
        "repeat": 36
      },
      {
        "name": "紫罗兰",
        "img": "./img/kpiflpo1sfdc1hi3uwoqu6ocv72tq72.png",
        "type": "时装",
        "description": "紫罗兰，风信子，薰衣草~~",
        "repeat": 36
      },
      {
        "name": "专注白",
        "img": "./img/fabvxpyjyshj3jm3mwbrhmbhbkyr7id.png",
        "type": "时装",
        "description": "没有专注，就没有精品!",
        "repeat": 36
      },
      {
        "name": "幽静蓝",
        "img": "./img/chpyas2owwi7brjdkogxg6robjfxhej.png",
        "type": "时装",
        "description": "即使在独处之时，也不能放松对自己的要求。",
        "repeat": 36
      },
      {
        "name": "天空蓝",
        "img": "./img/pqak28if48xz62d87oxfejl8jcgnmgf.png",
        "type": "时装",
        "description": "草垛上空的天空曾是他美好的回忆。",
        "repeat": 36
      },
      {
        "name": "骄阳",
        "img": "./img/sprkds8914i3qrlgb1n5mskv7uuuxra.png",
        "type": "时装",
        "description": "骄阳之下，谁还会回想起关于凛冬的往昔。",
        "repeat": 36
      },
      {
        "name": "夜宴灰",
        "img": "./img/ih6dwh3r5s4jjmw6umpajgp16nad9uz.png",
        "type": "时装",
        "description": "即使是接待男爵，也要优雅从容",
        "repeat": 36
      },
      {
        "name": "红藻",
        "img": "./img/bcn6uley7b4d30f2dj6h0jqffgiy81i.png",
        "type": "时装",
        "description": "旺盛的生机之下，湖泊已是一汪毒水。",
        "repeat": 36
      },
      {
        "name": "青苹果",
        "img": "./img/ig7dp4zyatgzb1tlo88enyqz7zzgaum.png",
        "type": "时装",
        "description": "青苹果虽然酸涩，但等它成熟就已被别人摘走了",
        "repeat": 36
      },
      {
        "name": "严肃蓝",
        "img": "./img/s7smh0clepavpl6q4ocfzkq258t4dap.png",
        "type": "时装",
        "description": "每一封信都会按时到达正确的地方!",
        "repeat": 36
      },
      {
        "name": "荒野白",
        "img": "./img/bjfwqv89aw0i6mxac18eia9pnt1uo57.png",
        "type": "时装",
        "description": "在荒野上，没人听得到你的祈祷。",
        "repeat": 36
      },
      {
        "name": "祭司-欢呼",
        "img": "./img/ch2gqfof6gfxxiyw1j0dn8u5gp8fz44.png",
        "type": "个性动作",
        "description": "欢呼动作，祭司专属",
        "repeat": 36
      },
      {
        "name": "空军-欢呼",
        "img": "./img/ch2gqfof6gfxxiyw1j0dn8u5gp8fz44.png",
        "type": "个性动作",
        "description": "欢呼动作，空军专属",
        "repeat": 36
      },
      {
        "name": "盲女-欢呼",
        "img": "./img/ch2gqfof6gfxxiyw1j0dn8u5gp8fz44.png",
        "type": "个性动作",
        "description": "欢呼动作，盲女专属",
        "repeat": 36
      },
      {
        "name": "前锋-欢呼",
        "img": "./img/ch2gqfof6gfxxiyw1j0dn8u5gp8fz44.png",
        "type": "个性动作",
        "description": "欢呼动作，前锋专属",
        "repeat": 36
      },
      {
        "name": "盲女-等待",
        "img": "./img/41a1wrtsip5iit54z0zhertp8lr5wsd.png",
        "type": "等待动作",
        "description": "盲女匹配大厅动作，等待",
        "repeat": 36
      },
      {
        "name": "机械师-等待",
        "img": "./img/41a1wrtsip5iit54z0zhertp8lr5wsd.png",
        "type": "等待动作",
        "description": "机械师匹配大厅动作，等待",
        "repeat": 36
      },
      {
        "name": "盲女-小憩",
        "img": "./img/41a1wrtsip5iit54z0zhertp8lr5wsd.png",
        "type": "等待动作",
        "description": "盲女匹配大厅动作，小憩",
        "repeat": 36
      },
      {
        "name": "机械师-小憩",
        "img": "./img/41a1wrtsip5iit54z0zhertp8lr5wsd.png",
        "type": "等待动作",
        "description": "机械师匹配大厅动作，小憩",
        "repeat": 36
      },
      {
        "name": "冒险家-小憩",
        "img": "./img/41a1wrtsip5iit54z0zhertp8lr5wsd.png",
        "type": "等待动作",
        "description": "冒险家匹配大厅动作，小憩",
        "repeat": 36
      },
      {
        "name": "祭司门之钥-卡通",
        "img": "./img/krauh5269d64rbklyzonf03u5w0bvuc.png",
        "type": "涂鸦",
        "description": "祭司专属涂鸦，卡通",
        "repeat": 36
      },
      {
        "name": "宿伞之魂铃铛-卡通",
        "img": "./img/mcfg8nei4ckjobkwwfeoeahmg2ugmik.png",
        "type": "涂鸦",
        "description": "宿伞之魂专属涂鸦，卡通",
        "repeat": 36
      },
      {
        "name": "小丑火箭-卡通",
        "img": "./img/ctyi53v7sgzi5row3emt455clvebczj.png",
        "type": "涂鸦",
        "description": "小丑专属涂鸦，卡通",
        "repeat": 36
      },
      {
        "name": "红蝶扇子-卡通",
        "img": "./img/7ke8xf5yktje1zov5nuja63ihb2wr6v.png",
        "type": "涂鸦",
        "description": "红蝶专属涂鸦，卡通",
        "repeat": 36
      },
      {
        "name": "黑白回忆-邮差",
        "img": "./img/j8a5d2j1ny800r1vox1on8dp4io9nn5.png",
        "type": "头像",
        "description": "黑白回忆系列头像\n“然而时光终成旧照，旧照褪为回忆，回忆消散于风中。”",
        "repeat": 36
      },
      {
        "name": "黑白回忆-守墓人",
        "img": "./img/cf16anw7vodznl9eyap6if7txs2q51s.png",
        "type": "头像",
        "description": "黑白回忆系列头像\n“然而时光终成旧照，旧照褪为回忆，回忆消散于风中。”",
        "repeat": 36
      },
      {
        "name": "黑白回忆-囚徒",
        "img": "./img/o5ft5goy3hpxppdhwn51i0g6kzs7ds1.png",
        "type": "头像",
        "description": "黑白回忆系列头像\n“然而时光终成旧照，旧照褪为回忆，回忆消散于风中。”",
        "repeat": 36
      }
    ],
    "D": [
      {
        "name": "摄影师-彩底",
        "img": "./img/mlj6abykiun16auloybdjgi4mv4jvxp.png",
        "type": "涂鸦",
        "description": "摄影师涂鸦，彩底",
        "repeat": 6
      },
      {
        "name": "“囚徒”-彩底",
        "img": "./img/7x82dv2pp1po8zhls62j0mqf3xxwlcn.png",
        "type": "涂鸦",
        "description": "“囚徒”涂鸦，彩底",
        "repeat": 6
      },
      {
        "name": "破轮-彩底",
        "img": "./img/hlojghbb184ye7pdfwulrwzuk5fsn41.png",
        "type": "涂鸦",
        "description": "破轮涂鸦，彩底",
        "repeat": 6
      },
      {
        "name": "调酒师-彩底",
        "img": "./img/kz1ggh29pmkmizft2jl9w3dt3i00dif.png",
        "type": "涂鸦",
        "description": "调酒师涂鸦，彩底",
        "repeat": 6
      },
      {
        "name": "大副-彩底",
        "img": "./img/fpyfasg6q8w3hilvf5u2vnqi1jlsmc4.png",
        "type": "涂鸦",
        "description": "大副涂鸦，彩底",
        "repeat": 6
      },
      {
        "name": "“博士”-彩底",
        "img": "./img/6in85zgy1dreqs0ehe606q0to5itpnw.png",
        "type": "涂鸦",
        "description": "“博士”涂鸦，彩底",
        "repeat": 6
      },
      {
        "name": "爱哭鬼-彩底",
        "img": "./img/rwwb0f8as6l2rb71c56gxitcx8zaarp.png",
        "type": "涂鸦",
        "description": "爱哭鬼涂鸦，彩底",
        "repeat": 6
      },
      {
        "name": "彩色回忆-爱哭鬼",
        "img": "./img/3fktxkodz5d8jqf69o36q4r8cmpdquy.png",
        "type": "头像",
        "description": "彩色回忆系列头像\n“记住这一瞬间的心情，并让这段时光永留在心底” ",
        "repeat": 6
      },
      {
        "name": "彩色回忆-囚徒",
        "img": "./img/5259wcf1u10co3aw50i9dondhbpt78j.png",
        "type": "头像",
        "description": "彩色回忆系列头像\n“记住这一瞬间的心情，并让这段时光永留在心底” ",
        "repeat": 6
      },
      {
        "name": "彩色回忆-守墓人",
        "img": "./img/i5kf58nap5nxmswp9jxtqy4cae8477d.png",
        "type": "头像",
        "description": "彩色回忆系列头像\n“记住这一瞬间的心情，并让这段时光永留在心底” ",
        "repeat": 6
      },
      {
        "name": "彩色回忆-邮差",
        "img": "./img/hd35a0l730req9j090vv4vaoi3qjk2c.png",
        "type": "头像",
        "description": "彩色回忆系列头像\n“记住这一瞬间的心情，并让这段时光永留在心底” ",
        "repeat": 6
      }
    ]
  }
}